chefboost/Chefboost.py
chefboost/__init__.py
chefboost/commons/__init__.py
chefboost/commons/daemon.py
chefboost/commons/evaluate.py
chefboost/commons/functions.py
chefboost/commons/logger.py
chefboost/commons/module.py
chefboost/training/Preprocess.py
chefboost/training/Training.py
chefboost/training/__init__.py
chefboost/tuning/__init__.py
chefboost/tuning/adaboost.py
chefboost/tuning/gbm.py
chefboost/tuning/randomforest.py
chefboost-0.0.19.dist-info/LICENSE
chefboost-0.0.19.dist-info/METADATA
chefboost-0.0.19.dist-info/WHEEL
chefboost-0.0.19.dist-info/top_level.txt
chefboost-0.0.19.dist-info/RECORD
