Metadata-Version: 2.1
Name: chefboost
Version: 0.0.19
Summary: Lightweight Decision Tree Framework Supporting GBM, Random Forest and Adaboost
Home-page: https://github.com/serengil/chefboost
Author: Sefik Ilkin Serengil
Author-email: serengil@gmail.com
License: UNKNOWN
Platform: UNKNOWN
Classifier: Programming Language :: Python :: 3
Classifier: License :: OSI Approved :: MIT License
Classifier: Operating System :: OS Independent
Requires-Python: >=3.6
License-File: LICENSE
Requires-Dist: pandas (>=0.22.0)
Requires-Dist: numpy (>=1.14.0)
Requires-Dist: tqdm (>=4.30.0)
Requires-Dist: psutil (>=5.4.3)
